{"rowCount":6,"colCount":6,"type":0,"letters":"تحصلى","words":[{"word":"حتى","vertical":false,"rowIndex":3,"colIndex":3,"coinIndices":[],"awardCoins":false},{"word":"تحصل","vertical":true,"rowIndex":2,"colIndex":3,"coinIndices":[],"awardCoins":false},{"word":"صلت","vertical":false,"rowIndex":0,"colIndex":0,"coinIndices":[],"awardCoins":false},{"word":"تصل","vertical":true,"rowIndex":0,"colIndex":2,"coinIndices":[],"awardCoins":false},{"word":"تصلح","vertical":false,"rowIndex":5,"colIndex":1,"coinIndices":[],"awardCoins":false},{"word":"تحصى","vertical":true,"rowIndex":0,"colIndex":5,"coinIndices":[],"awardCoins":false},{"word":"حصلت","vertical":false,"rowIndex":2,"colIndex":0,"coinIndices":[],"awardCoins":false},{"word":"حصى","vertical":true,"rowIndex":2,"colIndex":0,"coinIndices":[],"awardCoins":false}],"id":"ec788b97e6ac2d289c2b38c3dcbba4ff"}