{"rowCount":9,"colCount":9,"type":0,"letters":"اجرعم","words":[{"word":"جمع","vertical":true,"rowIndex":2,"colIndex":4,"coinIndices":[],"awardCoins":false},{"word":"مراجع","vertical":true,"rowIndex":4,"colIndex":5,"coinIndices":[],"awardCoins":false},{"word":"عام","vertical":true,"rowIndex":0,"colIndex":3,"coinIndices":[],"awardCoins":false},{"word":"عار","vertical":true,"rowIndex":3,"colIndex":1,"coinIndices":[],"awardCoins":false},{"word":"جرام","vertical":true,"rowIndex":0,"colIndex":0,"coinIndices":[],"awardCoins":false},{"word":"عما","vertical":false,"rowIndex":4,"colIndex":4,"coinIndices":[],"awardCoins":false},{"word":"عمر","vertical":true,"rowIndex":0,"colIndex":5,"coinIndices":[],"awardCoins":false},{"word":"عمرا","vertical":false,"rowIndex":0,"colIndex":5,"coinIndices":[],"awardCoins":false},{"word":"جامع","vertical":false,"rowIndex":0,"colIndex":0,"coinIndices":[],"awardCoins":false},{"word":"معراج","vertical":false,"rowIndex":6,"colIndex":2,"coinIndices":[],"awardCoins":false},{"word":"مرجعا","vertical":false,"rowIndex":8,"colIndex":2,"coinIndices":[],"awardCoins":false},{"word":"مجر","vertical":false,"rowIndex":2,"colIndex":3,"coinIndices":[],"awardCoins":false},{"word":"معا","vertical":false,"rowIndex":3,"colIndex":0,"coinIndices":[],"awardCoins":false}],"id":"7f7775e48136ed388e7ae5949a4aed08"}