{"rowCount":5,"colCount":6,"type":0,"letters":"أججرمهو","words":[{"word":"أهم","vertical":false,"rowIndex":1,"colIndex":3,"coinIndices":[],"awardCoins":false},{"word":"جورج","vertical":false,"rowIndex":2,"colIndex":0,"coinIndices":[],"awardCoins":false},{"word":"موجه","vertical":true,"rowIndex":1,"colIndex":1,"coinIndices":[],"awardCoins":false},{"word":"جمهور","vertical":true,"rowIndex":0,"colIndex":5,"coinIndices":[],"awardCoins":false},{"word":"أجور","vertical":true,"rowIndex":1,"colIndex":3,"coinIndices":[],"awardCoins":false}],"id":"b8f1d9151668d2b8f65e9d1358b8e60a"}