{"rowCount":5,"colCount":5,"type":0,"letters":"حصطلم","words":[{"word":"مصطلح","vertical":false,"rowIndex":2,"colIndex":0,"coinIndices":[],"awardCoins":false},{"word":"لمص","vertical":true,"rowIndex":2,"colIndex":3,"coinIndices":[],"awardCoins":false},{"word":"محل","vertical":true,"rowIndex":2,"colIndex":0,"coinIndices":[],"awardCoins":false},{"word":"حصل","vertical":false,"rowIndex":4,"colIndex":2,"coinIndices":[],"awardCoins":false},{"word":"صلح","vertical":true,"rowIndex":0,"colIndex":4,"coinIndices":[],"awardCoins":false}],"id":"e2b4e098314d704c5b696e9932172c2b"}