{"rowCount":6,"colCount":7,"type":0,"letters":"اتصلوو","words":[{"word":"توصل","vertical":true,"rowIndex":2,"colIndex":3,"coinIndices":[],"awardCoins":false},{"word":"توصلوا","vertical":false,"rowIndex":5,"colIndex":0,"coinIndices":[],"awardCoins":false},{"word":"تواصل","vertical":false,"rowIndex":3,"colIndex":2,"coinIndices":[],"awardCoins":false},{"word":"توصلا","vertical":true,"rowIndex":0,"colIndex":6,"coinIndices":[],"awardCoins":false},{"word":"وصلات","vertical":false,"rowIndex":0,"colIndex":2,"coinIndices":[],"awardCoins":false}],"id":"4e1eea9526c009bfdff64e915041a3e8"}