{"rowCount":5,"colCount":6,"type":0,"letters":"تحموى","words":[{"word":"حتى","vertical":true,"rowIndex":0,"colIndex":5,"coinIndices":[],"awardCoins":false},{"word":"محتوى","vertical":false,"rowIndex":2,"colIndex":1,"coinIndices":[],"awardCoins":false},{"word":"توى","vertical":false,"rowIndex":4,"colIndex":0,"coinIndices":[],"awardCoins":false},{"word":"محو","vertical":true,"rowIndex":2,"colIndex":1,"coinIndices":[],"awardCoins":false},{"word":"موت","vertical":true,"rowIndex":0,"colIndex":3,"coinIndices":[],"awardCoins":false}],"id":"efff3fd0a0d2af080736e60ad8a0117f"}