{"rowCount":6,"colCount":6,"type":0,"letters":"ءاخسفن","words":[{"word":"ساخن","vertical":false,"rowIndex":0,"colIndex":1,"coinIndices":[],"awardCoins":false},{"word":"خنفساء","vertical":true,"rowIndex":0,"colIndex":3,"coinIndices":[],"awardCoins":false},{"word":"سفن","vertical":true,"rowIndex":3,"colIndex":1,"coinIndices":[],"awardCoins":false},{"word":"خفاء","vertical":false,"rowIndex":2,"colIndex":2,"coinIndices":[],"awardCoins":false},{"word":"نفساء","vertical":false,"rowIndex":4,"colIndex":0,"coinIndices":[],"awardCoins":false}],"id":"026d73b0d063d91061bb3b917de5b5b6"}