{"rowCount":6,"colCount":6,"type":0,"letters":"تشمي","words":[{"word":"شي","vertical":false,"rowIndex":4,"colIndex":4,"coinIndices":[],"awardCoins":false},{"word":"يتم","vertical":false,"rowIndex":3,"colIndex":2,"coinIndices":[],"awardCoins":false},{"word":"تيم","vertical":false,"rowIndex":4,"colIndex":0,"coinIndices":[],"awardCoins":false},{"word":"شيت","vertical":true,"rowIndex":0,"colIndex":5,"coinIndices":[],"awardCoins":false},{"word":"ميت","vertical":true,"rowIndex":1,"colIndex":3,"coinIndices":[],"awardCoins":false},{"word":"متي","vertical":false,"rowIndex":1,"colIndex":3,"coinIndices":[],"awardCoins":false},{"word":"مشي","vertical":true,"rowIndex":3,"colIndex":4,"coinIndices":[],"awardCoins":false},{"word":"يمت","vertical":true,"rowIndex":3,"colIndex":2,"coinIndices":[],"awardCoins":false},{"word":"يشت","vertical":true,"rowIndex":2,"colIndex":0,"coinIndices":[],"awardCoins":false}],"id":"d4cd549f99256dcedbe2b4694775805f"}