{"rowCount":5,"colCount":6,"type":0,"letters":"بتطقن","words":[{"word":"تقط","vertical":true,"rowIndex":0,"colIndex":0,"coinIndices":[],"awardCoins":false},{"word":"تنطبق","vertical":false,"rowIndex":0,"colIndex":0,"coinIndices":[],"awardCoins":false},{"word":"طبقت","vertical":false,"rowIndex":4,"colIndex":2,"coinIndices":[],"awardCoins":false},{"word":"تنطق","vertical":false,"rowIndex":2,"colIndex":2,"coinIndices":[],"awardCoins":false},{"word":"بطن","vertical":true,"rowIndex":0,"colIndex":3,"coinIndices":[],"awardCoins":false},{"word":"نقطت","vertical":true,"rowIndex":1,"colIndex":5,"coinIndices":[],"awardCoins":false}],"id":"c6000b49203ea0ac6ecbb723d349df42"}