{"rowCount":8,"colCount":8,"type":0,"letters":"اابتحرلل","words":[{"word":"بالرحلات","vertical":true,"rowIndex":0,"colIndex":2,"coinIndices":[],"awardCoins":false},{"word":"احتلال","vertical":false,"rowIndex":4,"colIndex":1,"coinIndices":[],"awardCoins":false},{"word":"لرحلات","vertical":false,"rowIndex":2,"colIndex":2,"coinIndices":[],"awardCoins":false},{"word":"لحالات","vertical":false,"rowIndex":6,"colIndex":0,"coinIndices":[],"awardCoins":false},{"word":"بحرا","vertical":false,"rowIndex":0,"colIndex":2,"coinIndices":[],"awardCoins":false},{"word":"برتا","vertical":true,"rowIndex":0,"colIndex":7,"coinIndices":[],"awardCoins":false}],"id":"8c5834fa3e496a97e1134b127d7d33f1"}