{"rowCount":6,"colCount":6,"type":0,"letters":"تحقلي","words":[{"word":"تحليق","vertical":true,"rowIndex":1,"colIndex":3,"coinIndices":[],"awardCoins":false},{"word":"يلقح","vertical":false,"rowIndex":5,"colIndex":1,"coinIndices":[],"awardCoins":false},{"word":"حلقي","vertical":true,"rowIndex":1,"colIndex":5,"coinIndices":[],"awardCoins":false},{"word":"تلقيح","vertical":true,"rowIndex":0,"colIndex":0,"coinIndices":[],"awardCoins":false},{"word":"تلحق","vertical":false,"rowIndex":3,"colIndex":2,"coinIndices":[],"awardCoins":false},{"word":"لحقت","vertical":false,"rowIndex":1,"colIndex":0,"coinIndices":[],"awardCoins":false}],"id":"fa20dc855941911645b61f21bf5d73ef"}