{"rowCount":5,"colCount":5,"type":0,"letters":"تحلم","words":[{"word":"تحمل","vertical":true,"rowIndex":1,"colIndex":0,"coinIndices":[],"awardCoins":false},{"word":"حملت","vertical":true,"rowIndex":0,"colIndex":4,"coinIndices":[],"awardCoins":false},{"word":"محل","vertical":true,"rowIndex":2,"colIndex":2,"coinIndices":[],"awardCoins":false},{"word":"تملح","vertical":false,"rowIndex":0,"colIndex":1,"coinIndices":[],"awardCoins":false},{"word":"حلم","vertical":false,"rowIndex":2,"colIndex":0,"coinIndices":[],"awardCoins":false},{"word":"حمت","vertical":false,"rowIndex":3,"colIndex":2,"coinIndices":[],"awardCoins":false}],"id":"db55d1d9ef982a603ae8e652425668d5"}