{"rowCount":5,"colCount":6,"type":0,"letters":"اتطفقو","words":[{"word":"فقط","vertical":false,"rowIndex":1,"colIndex":0,"coinIndices":[],"awardCoins":false},{"word":"تطفوا","vertical":true,"rowIndex":0,"colIndex":2,"coinIndices":[],"awardCoins":false},{"word":"توقف","vertical":false,"rowIndex":0,"colIndex":2,"coinIndices":[],"awardCoins":false},{"word":"طفو","vertical":true,"rowIndex":0,"colIndex":0,"coinIndices":[],"awardCoins":false},{"word":"توافق","vertical":false,"rowIndex":4,"colIndex":0,"coinIndices":[],"awardCoins":false},{"word":"فوق","vertical":true,"rowIndex":2,"colIndex":4,"coinIndices":[],"awardCoins":false}],"id":"0c5ad9adaaabb1bd3761aec438e7b417"}