{"rowCount":5,"colCount":6,"type":0,"letters":"ترزسي","words":[{"word":"زيت","vertical":true,"rowIndex":0,"colIndex":0,"coinIndices":[],"awardCoins":false},{"word":"تسير","vertical":false,"rowIndex":2,"colIndex":0,"coinIndices":[],"awardCoins":false},{"word":"ترسي","vertical":true,"rowIndex":1,"colIndex":3,"coinIndices":[],"awardCoins":false},{"word":"سري","vertical":true,"rowIndex":2,"colIndex":1,"coinIndices":[],"awardCoins":false},{"word":"تسري","vertical":true,"rowIndex":0,"colIndex":5,"coinIndices":[],"awardCoins":false},{"word":"زير","vertical":false,"rowIndex":0,"colIndex":0,"coinIndices":[],"awardCoins":false},{"word":"ترس","vertical":false,"rowIndex":1,"colIndex":3,"coinIndices":[],"awardCoins":false}],"id":"3a63d3e71603bd1869fdefa33d200c54"}