{"rowCount":6,"colCount":6,"type":0,"letters":"ادرصصم","words":[{"word":"رصاص","vertical":false,"rowIndex":3,"colIndex":2,"coinIndices":[],"awardCoins":false},{"word":"صار","vertical":true,"rowIndex":3,"colIndex":5,"coinIndices":[],"awardCoins":false},{"word":"مصادر","vertical":false,"rowIndex":5,"colIndex":1,"coinIndices":[],"awardCoins":false},{"word":"صدر","vertical":false,"rowIndex":1,"colIndex":2,"coinIndices":[],"awardCoins":false},{"word":"رصد","vertical":false,"rowIndex":2,"colIndex":0,"coinIndices":[],"awardCoins":false},{"word":"مار","vertical":true,"rowIndex":0,"colIndex":0,"coinIndices":[],"awardCoins":false},{"word":"مصدر","vertical":true,"rowIndex":0,"colIndex":2,"coinIndices":[],"awardCoins":false}],"id":"042f48f6c61388268d6cafaa2e1c8310"}