{"rowCount":6,"colCount":7,"type":0,"letters":"أتدرفوىي","words":[{"word":"أدى","vertical":false,"rowIndex":0,"colIndex":4,"coinIndices":[],"awardCoins":false},{"word":"أفروديت","vertical":false,"rowIndex":2,"colIndex":0,"coinIndices":[],"awardCoins":false},{"word":"تدور","vertical":true,"rowIndex":2,"colIndex":6,"coinIndices":[],"awardCoins":false},{"word":"دور","vertical":false,"rowIndex":0,"colIndex":0,"coinIndices":[],"awardCoins":false},{"word":"وتفريد","vertical":true,"rowIndex":0,"colIndex":1,"coinIndices":[],"awardCoins":false},{"word":"توفر","vertical":false,"rowIndex":5,"colIndex":3,"coinIndices":[],"awardCoins":false},{"word":"أودي","vertical":true,"rowIndex":0,"colIndex":4,"coinIndices":[],"awardCoins":false}],"id":"b4983d81401d46eb37377a80cae185f6"}