{"rowCount":9,"colCount":10,"type":0,"letters":"ارعلميي","words":[{"word":"لمعايير","vertical":true,"rowIndex":2,"colIndex":2,"coinIndices":[],"awardCoins":false},{"word":"معايير","vertical":false,"rowIndex":5,"colIndex":0,"coinIndices":[],"awardCoins":false},{"word":"معياري","vertical":false,"rowIndex":3,"colIndex":2,"coinIndices":[],"awardCoins":false},{"word":"مليار","vertical":false,"rowIndex":7,"colIndex":0,"coinIndices":[],"awardCoins":false},{"word":"عمل","vertical":false,"rowIndex":2,"colIndex":0,"coinIndices":[],"awardCoins":false},{"word":"علم","vertical":true,"rowIndex":0,"colIndex":1,"coinIndices":[],"awardCoins":false},{"word":"يعمل","vertical":true,"rowIndex":3,"colIndex":7,"coinIndices":[],"awardCoins":false},{"word":"عالم","vertical":false,"rowIndex":0,"colIndex":1,"coinIndices":[],"awardCoins":false},{"word":"عار","vertical":true,"rowIndex":1,"colIndex":6,"coinIndices":[],"awardCoins":false},{"word":"عالي","vertical":false,"rowIndex":1,"colIndex":6,"coinIndices":[],"awardCoins":false},{"word":"علمي","vertical":false,"rowIndex":6,"colIndex":6,"coinIndices":[],"awardCoins":false}],"id":"57cd347f5b9acfe5e8e9fd55de35e64a"}