{"rowCount":7,"colCount":9,"type":0,"letters":"ئااترطني","words":[{"word":"طيران","vertical":true,"rowIndex":0,"colIndex":2,"coinIndices":[],"awardCoins":false},{"word":"طائرات","vertical":true,"rowIndex":1,"colIndex":6,"coinIndices":[],"awardCoins":false},{"word":"رئتين","vertical":false,"rowIndex":6,"colIndex":4,"coinIndices":[],"awardCoins":false},{"word":"تين","vertical":false,"rowIndex":4,"colIndex":0,"coinIndices":[],"awardCoins":false},{"word":"ري","vertical":true,"rowIndex":0,"colIndex":7,"coinIndices":[],"awardCoins":false},{"word":"تيران","vertical":false,"rowIndex":4,"colIndex":4,"coinIndices":[],"awardCoins":false},{"word":"طين","vertical":false,"rowIndex":1,"colIndex":6,"coinIndices":[],"awardCoins":false},{"word":"طني","vertical":false,"rowIndex":1,"colIndex":0,"coinIndices":[],"awardCoins":false},{"word":"طيار","vertical":false,"rowIndex":0,"colIndex":2,"coinIndices":[],"awardCoins":false},{"word":"ريانا","vertical":false,"rowIndex":2,"colIndex":2,"coinIndices":[],"awardCoins":false}],"id":"3c20ff234f0c95a43c02100cda81456a"}