{"rowCount":9,"colCount":10,"type":0,"letters":"أاكمن","words":[{"word":"كان","vertical":false,"rowIndex":4,"colIndex":5,"coinIndices":[],"awardCoins":false},{"word":"أماكن","vertical":true,"rowIndex":0,"colIndex":7,"coinIndices":[],"awardCoins":false},{"word":"أمان","vertical":false,"rowIndex":7,"colIndex":0,"coinIndices":[],"awardCoins":false},{"word":"مكان","vertical":false,"rowIndex":5,"colIndex":2,"coinIndices":[],"awardCoins":false},{"word":"كما","vertical":false,"rowIndex":3,"colIndex":7,"coinIndices":[],"awardCoins":false},{"word":"أكان","vertical":true,"rowIndex":4,"colIndex":3,"coinIndices":[],"awardCoins":false},{"word":"أما","vertical":true,"rowIndex":6,"colIndex":1,"coinIndices":[],"awardCoins":false},{"word":"أمنا","vertical":false,"rowIndex":1,"colIndex":6,"coinIndices":[],"awardCoins":false},{"word":"أمكن","vertical":true,"rowIndex":2,"colIndex":5,"coinIndices":[],"awardCoins":false}],"id":"2d9384284376246706bb1717f825eb70"}